{
    "Farin": {
        "Farin1xQZru5XBoGR0sR/BSGa8uA==": [
            [
                "help",
                "get in here",
                "i need you"
            ],
            [
                "What do you need of me @author? Someone need to be assassinated?"
            ]
        ],
        "Farin2+t4OoQSi5v/M/HgsWAepbA==": [
            [
                "how are you?"
            ],
            [
                "I am not obligated to give you an answer, peasent."
            ]
        ]
    },
    "Any": {
        "Any1xQZru5XBoGR0sR/BSGa8uA==": [
            [
                "crying"
            ],
            [
                "*\\*drinks tears\\**"
            ]
        ],
        "Any2xQZru5XBoGR0sR/BSGa8uA==": [
            [
                "death",
                "dead",
                "destruction",
                "kill",
                "dying",
                "die",
                "murder",
                "blood"
            ],
            [
                "*\\*interest peaks\\**"
            ]
        ]
    }
}